{
  "annotations": {
    "list": [
      {
        "builtIn": 1,
        "datasource": "-- Grafana --",
        "enable": true,
        "hide": true,
        "iconColor": "rgba(0, 211, 255, 1)",
        "name": "Annotations & Alerts",
        "target": {
          "limit": 100,
          "matchAny": false,
          "tags": [],
          "type": "dashboard"
        },
        "type": "dashboard"
      }
    ]
  },
  "editable": true,
  "fiscalYearStartMonth": 0,
  "graphTooltip": 1,
  "id": 376,
  "links": [],
  "liveNow": false,
  "panels": [
    {
      "fieldConfig": {
        "defaults": {
          "color": {
            "mode": "palette-classic"
          },
          "custom": {
            "axisLabel": "",
            "axisPlacement": "auto",
            "barAlignment": 0,
            "drawStyle": "line",
            "fillOpacity": 0,
            "gradientMode": "none",
            "hideFrom": {
              "legend": false,
              "tooltip": false,
              "viz": false
            },
            "lineInterpolation": "linear",
            "lineWidth": 1,
            "pointSize": 3,
            "scaleDistribution": {
              "type": "linear"
            },
            "showPoints": "auto",
            "spanNulls": true,
            "stacking": {
              "group": "A",
              "mode": "none"
            },
            "thresholdsStyle": {
              "mode": "off"
            }
          },
          "mappings": [],
          "max": 100,
          "thresholds": {
            "mode": "absolute",
            "steps": [
              {
                "color": "green",
                "value": null
              },
              {
                "color": "red",
                "value": 80
              }
            ]
          },
          "unit": "percent"
        },
        "overrides": []
      },
      "gridPos": {
        "h": 11,
        "w": 24,
        "x": 0,
        "y": 0
      },
      "id": 2,
      "interval": "2m",
      "options": {
        "legend": {
          "calcs": [
            "last"
          ],
          "displayMode": "table",
          "placement": "bottom",
          "sortBy": "Last",
          "sortDesc": true
        },
        "tooltip": {
          "mode": "multi"
        }
      },
      "targets": [
        {
          "datasource": {
            "type": "prometheus",
            "uid": "000000001"
          },
          "exemplar": true,
          "expr": "(\r\n(count(\r\n    count(node_cpu_seconds_total{kubernetes_node=~\".+\"}) by (kubernetes_node, cpu) \r\n) by (kubernetes_node)\r\n-\r\navg(\r\n    sum(\r\n        irate(node_cpu_seconds_total{mode='idle',kubernetes_node=~\".+\"}[$__rate_interval])\r\n    ) by (mode, kubernetes_node)\r\n) by (kubernetes_node)) *100\r\n)\r\n/\r\n(count(\r\n    count(node_cpu_seconds_total{kubernetes_node=~\".+\"}) by (kubernetes_node, cpu) \r\n) by (kubernetes_node))",
          "hide": false,
          "interval": "",
          "legendFormat": "{{kubernetes_node}}",
          "refId": "B"
        }
      ],
      "title": "CPU USAGE %",
      "type": "timeseries"
    },
    {
      "fieldConfig": {
        "defaults": {
          "color": {
            "mode": "palette-classic"
          },
          "custom": {
            "axisLabel": "",
            "axisPlacement": "auto",
            "barAlignment": 0,
            "drawStyle": "line",
            "fillOpacity": 0,
            "gradientMode": "none",
            "hideFrom": {
              "legend": false,
              "tooltip": false,
              "viz": false
            },
            "lineInterpolation": "linear",
            "lineStyle": {
              "fill": "solid"
            },
            "lineWidth": 1,
            "pointSize": 3,
            "scaleDistribution": {
              "type": "linear"
            },
            "showPoints": "auto",
            "spanNulls": true,
            "stacking": {
              "group": "A",
              "mode": "none"
            },
            "thresholdsStyle": {
              "mode": "off"
            }
          },
          "mappings": [],
          "max": 100,
          "thresholds": {
            "mode": "absolute",
            "steps": [
              {
                "color": "green",
                "value": null
              },
              {
                "color": "red",
                "value": 80
              }
            ]
          },
          "unit": "percent"
        },
        "overrides": []
      },
      "gridPos": {
        "h": 11,
        "w": 24,
        "x": 0,
        "y": 11
      },
      "id": 4,
      "options": {
        "legend": {
          "calcs": [
            "last"
          ],
          "displayMode": "table",
          "placement": "bottom",
          "sortBy": "Last",
          "sortDesc": true
        },
        "tooltip": {
          "mode": "multi"
        }
      },
      "targets": [
        {
          "datasource": {
            "type": "prometheus",
            "uid": "000000001"
          },
          "exemplar": true,
          "expr": "((node_memory_MemTotal_bytes{kubernetes_node=~\".+\"} - node_memory_MemFree_bytes{kubernetes_node=~\".+\"} - (node_memory_Cached_bytes{kubernetes_node=~\".+\"} + node_memory_Buffers_bytes{kubernetes_node=~\".+\"} + node_memory_SReclaimable_bytes{kubernetes_node=~\".+\"})) / node_memory_MemTotal_bytes{kubernetes_node=~\".+\"} )*100",
          "hide": false,
          "interval": "",
          "legendFormat": "{{kubernetes_node}}",
          "refId": "B"
        }
      ],
      "title": "MEM USAGE %",
      "type": "timeseries"
    }
  ],
  "refresh": "",
  "schemaVersion": 34,
  "style": "dark",
  "tags": [],
  "templating": {
    "list": []
  },
  "time": {
    "from": "now-5m",
    "to": "now"
  },
  "timepicker": {},
  "timezone": "",
  "title": "K8s-nodes",
  "uid": "9gZWwViVz",
  "version": 11,
  "weekStart": ""
}
